{
    "@context": "https://doi.org/10.5063/schema/codemeta-2.0",
    "@type": "SoftwareSourceCode",
    "description": "An experimental set of command line tools for web content generation and publishing using Markdown, Golang template and Blevesearch library.",
    "name": "mkpage",
    "codeRepository": "https://github.com/caltechlibrary/mkpage",
    "issueTracker": "https://github.com/caltechlibrary/mkpage/issues",
    "license": "https://data.caltech.edu/license",
    "version": "0.0.25",
    "author": [
        {
            "@type": "Person",
            "givenName": "Robert",
            "familyName": "Doiel",
            "affiliation": "Caltech Library",
            "email": "rsdoiel@caltech.edu",
            "@id": "https://orcid.org/0000-0003-0900-6903"
        }
    ],
    "developmentStatus": "active",
    "downloadUrl": "https://github.com/caltechlibrary/mkpage/releases",
    "keywords": [
        "content management",
        "webpage generation",
        "web server",
        "blogging",
        "slides",
        "markdown"
    ],
    "maintainer": "https://orcid.org/0000-0003-0900-6903",
    "programmingLanguage": [
        "Go"
    ]
}